MANIFEST.in
README.rst
README.txt
dev_requirements.txt
requirements.txt
setup.py
test_requirements.txt
version.txt
cloudshell/__init__.py
cloudshell/traffic/__init__.py
cloudshell/traffic/virtual/__init__.py
cloudshell/traffic/virtual/resource_driver_interface.py
cloudshell/traffic/virtual/flows/__init__.py
cloudshell/traffic/virtual/flows/connect_child_resources.py
cloudshell/traffic/virtual/flows/get_ports.py
cloudshell/traffic/virtual/runners/__init__.py
cloudshell/traffic/virtual/runners/connect_child_resources.py
cloudshell_traffic_virtual.egg-info/PKG-INFO
cloudshell_traffic_virtual.egg-info/SOURCES.txt
cloudshell_traffic_virtual.egg-info/dependency_links.txt
cloudshell_traffic_virtual.egg-info/requires.txt
cloudshell_traffic_virtual.egg-info/top_level.txt
tests/__init__.py